libs/__init__.py
libs/field_mappers/__init__.py
libs/field_mappers/static_mappers.py
libs/google_sheets/__init__.py
libs/google_sheets/client.py
libs/google_sheets/config.py
libs/service_account/__init__.py
libs/service_account/config.py
libs/sftp/__init__.py
libs/sftp/client.py
libs/trino/__init__.py
libs/trino/client.py
libs/trino/config.py
cs_workflows_helper_libs-1.0.1.dist-info/METADATA
cs_workflows_helper_libs-1.0.1.dist-info/WHEEL
cs_workflows_helper_libs-1.0.1.dist-info/RECORD
